{
  "disco": {
    "10": {
      "Errors": 0,
      "Max Discovery Time Delta": 3.310454,
      "Discovery Time Delta": {
        "count": 360,
        "min": 0.10023,
        "max": 3.310454,
        "mean": 2.466932,
        "stdev": 1.238025,
        "median": 3.163308,
        "madev": 0.051336,
        "overflow": 0
      },
      "Cpu Utilization": {
        "count": 160,
        "min": 0,
        "max": 3.544304,
        "mean": 0.294883,
        "stdev": 0.796437,
        "median": 0,
        "madev": 0,
        "overflow": 0
      },
      "Memory Utilization": {
        "count": 160,
        "min": 0,
        "max": 1.458583,
        "mean": 1.277631,
        "stdev": 0.331943,
        "median": 1.335493,
        "madev": 0.014244,
        "overflow": 0
      },
      "Virtual Memory Utilization": {
        "count": 160,
        "min": 0,
        "max": 0.002251,
        "mean": 0.001958,
        "stdev": 0.000506,
        "median": 0.002084,
        "madev": 0,
        "overflow": 0
      },
      "Latency": {
        "count": 0,
        "min": 0,
        "max": 0,
        "mean": 0,
        "stdev": 0,
        "median": 0,
        "madev": 0,
        "overflow": 0
      },
      "Jitter": {
        "count": 0,
        "min": 0,
        "max": 0,
        "mean": 0,
        "stdev": 0,
        "median": 0,
        "madev": 0,
        "overflow": 0
      },
      "Round Trip Latency": {
        "count": 0,
        "min": 0,
        "max": 0,
        "mean": 0,
        "stdev": 0,
        "median": 0,
        "madev": 0,
        "overflow": 0
      },
      "Round Trip Jitter": {
        "count": 0,
        "min": 0,
        "max": 0,
        "mean": 0,
        "stdev": 0,
        "median": 0,
        "madev": 0,
        "overflow": 0
      }
    },
    "20": {
      "Errors": 0,
      "Max Discovery Time Delta": 3.332047,
      "Discovery Time Delta": {
        "count": 1520,
        "min": 0.0974,
        "max": 3.332047,
        "mean": 2.865839,
        "stdev": 0.885832,
        "median": 3.161318,
        "madev": 0.056811,
        "overflow": 0
      },
      "Cpu Utilization": {
        "count": 320,
        "min": 0,
        "max": 3.778338,
        "mean": 0.393052,
        "stdev": 0.978251,
        "median": 0,
        "madev": 0,
        "overflow": 0
      },
      "Memory Utilization": {
        "count": 320,
        "min": 0,
        "max": 1.565304,
        "mean": 1.328149,
        "stdev": 0.344815,
        "median": 1.408731,
        "madev": 0.062183,
        "overflow": 0
      },
      "Virtual Memory Utilization": {
        "count": 320,
        "min": 0,
        "max": 0.002251,
        "mean": 0.001956,
        "stdev": 0.000505,
        "median": 0.002084,
        "madev": 0,
        "overflow": 0
      },
      "Latency": {
        "count": 0,
        "min": 0,
        "max": 0,
        "mean": 0,
        "stdev": 0,
        "median": 0,
        "madev": 0,
        "overflow": 0
      },
      "Jitter": {
        "count": 0,
        "min": 0,
        "max": 0,
        "mean": 0,
        "stdev": 0,
        "median": 0,
        "madev": 0,
        "overflow": 0
      },
      "Round Trip Latency": {
        "count": 0,
        "min": 0,
        "max": 0,
        "mean": 0,
        "stdev": 0,
        "median": 0,
        "madev": 0,
        "overflow": 0
      },
      "Round Trip Jitter": {
        "count": 0,
        "min": 0,
        "max": 0,
        "mean": 0,
        "stdev": 0,
        "median": 0,
        "madev": 0,
        "overflow": 0
      }
    },
    "40": {
      "Errors": 0,
      "Max Discovery Time Delta": 4.441927,
      "Discovery Time Delta": {
        "count": 6240,
        "min": 0.096443,
        "max": 4.441927,
        "mean": 2.854889,
        "stdev": 1.025519,
        "median": 3.243659,
        "madev": 0.08694,
        "overflow": 0
      },
      "Cpu Utilization": {
        "count": 504,
        "min": 0,
        "max": 13.010204,
        "mean": 0.873319,
        "stdev": 2.299537,
        "median": 0,
        "madev": 0,
        "overflow": 0
      },
      "Memory Utilization": {
        "count": 504,
        "min": 0,
        "max": 2.997738,
        "mean": 1.775847,
        "stdev": 0.487776,
        "median": 1.498763,
        "madev": 0.108421,
        "overflow": 0
      },
      "Virtual Memory Utilization": {
        "count": 504,
        "min": 0,
        "max": 0.004335,
        "mean": 0.002603,
        "stdev": 0.000715,
        "median": 0.002084,
        "madev": 0,
        "overflow": 0
      },
      "Latency": {
        "count": 0,
        "min": 0,
        "max": 0,
        "mean": 0,
        "stdev": 0,
        "median": 0,
        "madev": 0,
        "overflow": 0
      },
      "Jitter": {
        "count": 0,
        "min": 0,
        "max": 0,
        "mean": 0,
        "stdev": 0,
        "median": 0,
        "madev": 0,
        "overflow": 0
      },
      "Round Trip Latency": {
        "count": 0,
        "min": 0,
        "max": 0,
        "mean": 0,
        "stdev": 0,
        "median": 0,
        "madev": 0,
        "overflow": 0
      },
      "Round Trip Jitter": {
        "count": 0,
        "min": 0,
        "max": 0,
        "mean": 0,
        "stdev": 0,
        "median": 0,
        "madev": 0,
        "overflow": 0
      }
    },
    "60": {
      "Errors": 0,
      "Max Discovery Time Delta": 4.446649,
      "Discovery Time Delta": {
        "count": 14160,
        "min": 0.095013,
        "max": 4.446649,
        "mean": 2.992982,
        "stdev": 0.997677,
        "median": 3.358799,
        "madev": 0.07714,
        "overflow": 0
      },
      "Cpu Utilization": {
        "count": 494,
        "min": 0,
        "max": 22.391858,
        "mean": 1.8853,
        "stdev": 4.868256,
        "median": 0,
        "madev": 0,
        "overflow": 0
      },
      "Memory Utilization": {
        "count": 494,
        "min": 0,
        "max": 3.283247,
        "mean": 2.699927,
        "stdev": 0.725989,
        "median": 2.866782,
        "madev": 0.092477,
        "overflow": 0
      },
      "Virtual Memory Utilization": {
        "count": 494,
        "min": 0,
        "max": 0.004502,
        "mean": 0.003872,
        "stdev": 0.001031,
        "median": 0.004168,
        "madev": 0,
        "overflow": 0
      },
      "Latency": {
        "count": 0,
        "min": 0,
        "max": 0,
        "mean": 0,
        "stdev": 0,
        "median": 0,
        "madev": 0,
        "overflow": 0
      },
      "Jitter": {
        "count": 0,
        "min": 0,
        "max": 0,
        "mean": 0,
        "stdev": 0,
        "median": 0,
        "madev": 0,
        "overflow": 0
      },
      "Round Trip Latency": {
        "count": 0,
        "min": 0,
        "max": 0,
        "mean": 0,
        "stdev": 0,
        "median": 0,
        "madev": 0,
        "overflow": 0
      },
      "Round Trip Jitter": {
        "count": 0,
        "min": 0,
        "max": 0,
        "mean": 0,
        "stdev": 0,
        "median": 0,
        "madev": 0,
        "overflow": 0
      }
    },
    "80": {
      "Errors": 0,
      "Max Discovery Time Delta": 5.227157,
      "Discovery Time Delta": {
        "count": 25280,
        "min": 0.089741,
        "max": 5.227157,
        "mean": 3.213101,
        "stdev": 0.927413,
        "median": 3.453312,
        "madev": 0.097937,
        "overflow": 0
      },
      "Cpu Utilization": {
        "count": 517,
        "min": 0,
        "max": 39.220779,
        "mean": 2.896325,
        "stdev": 7.88486,
        "median": 0,
        "madev": 0,
        "overflow": 0
      },
      "Memory Utilization": {
        "count": 517,
        "min": 0,
        "max": 4.782648,
        "mean": 3.722722,
        "stdev": 0.981006,
        "median": 4.363207,
        "madev": 0.239377,
        "overflow": 0
      },
      "Virtual Memory Utilization": {
        "count": 517,
        "min": 0,
        "max": 0.006753,
        "mean": 0.005204,
        "stdev": 0.001362,
        "median": 0.006252,
        "madev": 0,
        "overflow": 0
      },
      "Latency": {
        "count": 0,
        "min": 0,
        "max": 0,
        "mean": 0,
        "stdev": 0,
        "median": 0,
        "madev": 0,
        "overflow": 0
      },
      "Jitter": {
        "count": 0,
        "min": 0,
        "max": 0,
        "mean": 0,
        "stdev": 0,
        "median": 0,
        "madev": 0,
        "overflow": 0
      },
      "Round Trip Latency": {
        "count": 0,
        "min": 0,
        "max": 0,
        "mean": 0,
        "stdev": 0,
        "median": 0,
        "madev": 0,
        "overflow": 0
      },
      "Round Trip Jitter": {
        "count": 0,
        "min": 0,
        "max": 0,
        "mean": 0,
        "stdev": 0,
        "median": 0,
        "madev": 0,
        "overflow": 0
      }
    },
    "100": {
      "Errors": 0,
      "Max Discovery Time Delta": 5.770192,
      "Discovery Time Delta": {
        "count": 39600,
        "min": 0.083235,
        "max": 5.770192,
        "mean": 3.265013,
        "stdev": 0.891529,
        "median": 3.538693,
        "madev": 0.100137,
        "overflow": 0
      },
      "Cpu Utilization": {
        "count": 515,
        "min": 0,
        "max": 65.572358,
        "mean": 4.312388,
        "stdev": 12.422751,
        "median": 0,
        "madev": 0,
        "overflow": 0
      },
      "Memory Utilization": {
        "count": 515,
        "min": 0,
        "max": 6.182768,
        "mean": 4.68917,
        "stdev": 1.255276,
        "median": 4.686982,
        "madev": 0.279131,
        "overflow": 0
      },
      "Virtual Memory Utilization": {
        "count": 515,
        "min": 0,
        "max": 0.008646,
        "mean": 0.006494,
        "stdev": 0.001725,
        "median": 0.006252,
        "madev": 0,
        "overflow": 0
      },
      "Latency": {
        "count": 0,
        "min": 0,
        "max": 0,
        "mean": 0,
        "stdev": 0,
        "median": 0,
        "madev": 0,
        "overflow": 0
      },
      "Jitter": {
        "count": 0,
        "min": 0,
        "max": 0,
        "mean": 0,
        "stdev": 0,
        "median": 0,
        "madev": 0,
        "overflow": 0
      },
      "Round Trip Latency": {
        "count": 0,
        "min": 0,
        "max": 0,
        "mean": 0,
        "stdev": 0,
        "median": 0,
        "madev": 0,
        "overflow": 0
      },
      "Round Trip Jitter": {
        "count": 0,
        "min": 0,
        "max": 0,
        "mean": 0,
        "stdev": 0,
        "median": 0,
        "madev": 0,
        "overflow": 0
      }
    },
    "120": {
      "Errors": 0,
      "Max Discovery Time Delta": 5.917045,
      "Discovery Time Delta": {
        "count": 57120,
        "min": 0.055507,
        "max": 5.917045,
        "mean": 3.384867,
        "stdev": 0.897453,
        "median": 3.630012,
        "madev": 0.14329,
        "overflow": 0
      },
      "Cpu Utilization": {
        "count": 542,
        "min": 0,
        "max": 86.125654,
        "mean": 5.81699,
        "stdev": 17.212756,
        "median": 0,
        "madev": 0,
        "overflow": 0
      },
      "Memory Utilization": {
        "count": 542,
        "min": 0,
        "max": 6.530354,
        "mean": 5.700284,
        "stdev": 1.436216,
        "median": 6.137699,
        "madev": 0.134357,
        "overflow": 0
      },
      "Virtual Memory Utilization": {
        "count": 542,
        "min": 0,
        "max": 0.008813,
        "mean": 0.007847,
        "stdev": 0.00195,
        "median": 0.008337,
        "madev": 0,
        "overflow": 0
      },
      "Latency": {
        "count": 0,
        "min": 0,
        "max": 0,
        "mean": 0,
        "stdev": 0,
        "median": 0,
        "madev": 0,
        "overflow": 0
      },
      "Jitter": {
        "count": 0,
        "min": 0,
        "max": 0,
        "mean": 0,
        "stdev": 0,
        "median": 0,
        "madev": 0,
        "overflow": 0
      },
      "Round Trip Latency": {
        "count": 0,
        "min": 0,
        "max": 0,
        "mean": 0,
        "stdev": 0,
        "median": 0,
        "madev": 0,
        "overflow": 0
      },
      "Round Trip Jitter": {
        "count": 0,
        "min": 0,
        "max": 0,
        "mean": 0,
        "stdev": 0,
        "median": 0,
        "madev": 0,
        "overflow": 0
      }
    },
    "140": {
      "Errors": 0,
      "Max Discovery Time Delta": 5.90367,
      "Discovery Time Delta": {
        "count": 77840,
        "min": 0.066775,
        "max": 5.90367,
        "mean": 3.642782,
        "stdev": 0.717669,
        "median": 3.806007,
        "madev": 0.153579,
        "overflow": 0
      },
      "Cpu Utilization": {
        "count": 543,
        "min": 0,
        "max": 95.557091,
        "mean": 7.690788,
        "stdev": 20.531747,
        "median": 0,
        "madev": 0,
        "overflow": 0
      },
      "Memory Utilization": {
        "count": 543,
        "min": 0,
        "max": 8.17389,
        "mean": 6.546545,
        "stdev": 1.917376,
        "median": 7.016761,
        "madev": 0.796576,
        "overflow": 0
      },
      "Virtual Memory Utilization": {
        "count": 543,
        "min": 0,
        "max": 0.010921,
        "mean": 0.008857,
        "stdev": 0.002556,
        "median": 0.010397,
        "madev": 0.000167,
        "overflow": 0
      },
      "Latency": {
        "count": 0,
        "min": 0,
        "max": 0,
        "mean": 0,
        "stdev": 0,
        "median": 0,
        "madev": 0,
        "overflow": 0
      },
      "Jitter": {
        "count": 0,
        "min": 0,
        "max": 0,
        "mean": 0,
        "stdev": 0,
        "median": 0,
        "madev": 0,
        "overflow": 0
      },
      "Round Trip Latency": {
        "count": 0,
        "min": 0,
        "max": 0,
        "mean": 0,
        "stdev": 0,
        "median": 0,
        "madev": 0,
        "overflow": 0
      },
      "Round Trip Jitter": {
        "count": 0,
        "min": 0,
        "max": 0,
        "mean": 0,
        "stdev": 0,
        "median": 0,
        "madev": 0,
        "overflow": 0
      }
    },
    "160": {
      "Errors": 0,
      "Max Discovery Time Delta": 5.839613,
      "Discovery Time Delta": {
        "count": 101760,
        "min": 0.057537,
        "max": 5.839613,
        "mean": 3.771221,
        "stdev": 0.664902,
        "median": 3.891503,
        "madev": 0.184486,
        "overflow": 0
      },
      "Cpu Utilization": {
        "count": 542,
        "min": 0,
        "max": 100,
        "mean": 9.048957,
        "stdev": 22.033421,
        "median": 0.25,
        "madev": 0.25,
        "overflow": 0
      },
      "Memory Utilization": {
        "count": 542,
        "min": 0,
        "max": 9.734517,
        "mean": 7.810706,
        "stdev": 2.006417,
        "median": 8.108625,
        "madev": 0.296351,
        "overflow": 0
      },
      "Virtual Memory Utilization": {
        "count": 542,
        "min": 0,
        "max": 0.013125,
        "mean": 0.010416,
        "stdev": 0.002616,
        "median": 0.010421,
        "madev": 0,
        "overflow": 0
      },
      "Latency": {
        "count": 0,
        "min": 0,
        "max": 0,
        "mean": 0,
        "stdev": 0,
        "median": 0,
        "madev": 0,
        "overflow": 0
      },
      "Jitter": {
        "count": 0,
        "min": 0,
        "max": 0,
        "mean": 0,
        "stdev": 0,
        "median": 0,
        "madev": 0,
        "overflow": 0
      },
      "Round Trip Latency": {
        "count": 0,
        "min": 0,
        "max": 0,
        "mean": 0,
        "stdev": 0,
        "median": 0,
        "madev": 0,
        "overflow": 0
      },
      "Round Trip Jitter": {
        "count": 0,
        "min": 0,
        "max": 0,
        "mean": 0,
        "stdev": 0,
        "median": 0,
        "madev": 0,
        "overflow": 0
      }
    },
    "180": {
      "Errors": 0,
      "Max Discovery Time Delta": 5.99183,
      "Discovery Time Delta": {
        "count": 128880,
        "min": 0.006206,
        "max": 5.99183,
        "mean": 3.915474,
        "stdev": 0.689363,
        "median": 4.017489,
        "madev": 0.207374,
        "overflow": 0
      },
      "Cpu Utilization": {
        "count": 550,
        "min": 0,
        "max": 99.798239,
        "mean": 11.412967,
        "stdev": 23.986372,
        "median": 0.25,
        "madev": 0.25,
        "overflow": 0
      },
      "Memory Utilization": {
        "count": 550,
        "min": 0,
        "max": 10.114629,
        "mean": 8.765333,
        "stdev": 2.408888,
        "median": 9.689023,
        "madev": 0.177513,
        "overflow": 0
      },
      "Virtual Memory Utilization": {
        "count": 550,
        "min": 0,
        "max": 0.013125,
        "mean": 0.011497,
        "stdev": 0.003081,
        "median": 0.012505,
        "madev": 0,
        "overflow": 0
      },
      "Latency": {
        "count": 0,
        "min": 0,
        "max": 0,
        "mean": 0,
        "stdev": 0,
        "median": 0,
        "madev": 0,
        "overflow": 0
      },
      "Jitter": {
        "count": 0,
        "min": 0,
        "max": 0,
        "mean": 0,
        "stdev": 0,
        "median": 0,
        "madev": 0,
        "overflow": 0
      },
      "Round Trip Latency": {
        "count": 0,
        "min": 0,
        "max": 0,
        "mean": 0,
        "stdev": 0,
        "median": 0,
        "madev": 0,
        "overflow": 0
      },
      "Round Trip Jitter": {
        "count": 0,
        "min": 0,
        "max": 0,
        "mean": 0,
        "stdev": 0,
        "median": 0,
        "madev": 0,
        "overflow": 0
      }
    },
    "200": {
      "Errors": 0,
      "Max Discovery Time Delta": 6.445906,
      "Discovery Time Delta": {
        "count": 159200,
        "min": 0.038442,
        "max": 6.445906,
        "mean": 4.074895,
        "stdev": 0.582388,
        "median": 4.15433,
        "madev": 0.224897,
        "overflow": 0
      },
      "Cpu Utilization": {
        "count": 570,
        "min": 0,
        "max": 102.647274,
        "mean": 12.836302,
        "stdev": 25.610983,
        "median": 0.25,
        "madev": 0.25,
        "overflow": 0
      },
      "Memory Utilization": {
        "count": 570,
        "min": 0,
        "max": 11.990102,
        "mean": 9.856676,
        "stdev": 2.88255,
        "median": 10.409704,
        "madev": 1.241316,
        "overflow": 0
      },
      "Virtual Memory Utilization": {
        "count": 570,
        "min": 0,
        "max": 0.015042,
        "mean": 0.012576,
        "stdev": 0.00359,
        "median": 0.014398,
        "madev": 0.000191,
        "overflow": 0
      },
      "Latency": {
        "count": 0,
        "min": 0,
        "max": 0,
        "mean": 0,
        "stdev": 0,
        "median": 0,
        "madev": 0,
        "overflow": 0
      },
      "Jitter": {
        "count": 0,
        "min": 0,
        "max": 0,
        "mean": 0,
        "stdev": 0,
        "median": 0,
        "madev": 0,
        "overflow": 0
      },
      "Round Trip Latency": {
        "count": 0,
        "min": 0,
        "max": 0,
        "mean": 0,
        "stdev": 0,
        "median": 0,
        "madev": 0,
        "overflow": 0
      },
      "Round Trip Jitter": {
        "count": 0,
        "min": 0,
        "max": 0,
        "mean": 0,
        "stdev": 0,
        "median": 0,
        "madev": 0,
        "overflow": 0
      }
    },
    "320": {
      "Errors": 1,
      "Max Discovery Time Delta": 9.505252,
      "Discovery Time Delta": {
        "count": 404166,
        "min": 0.019878,
        "max": 9.505252,
        "mean": 6.043824,
        "stdev": 1.089729,
        "median": 6.215352,
        "madev": 0.729296,
        "overflow": 0
      },
      "Cpu Utilization": {
        "count": 4023,
        "min": 0,
        "max": 107.795699,
        "mean": 5.490535,
        "stdev": 19.968581,
        "median": 0.250627,
        "madev": 0.250627,
        "overflow": 0
      },
      "Memory Utilization": {
        "count": 4023,
        "min": 0,
        "max": 20.897004,
        "mean": 14.035018,
        "stdev": 2.832331,
        "median": 14.686387,
        "madev": 2.226035,
        "overflow": 0
      },
      "Virtual Memory Utilization": {
        "count": 4023,
        "min": 0,
        "max": 0.023521,
        "mean": 0.015706,
        "stdev": 0.003396,
        "median": 0.016482,
        "madev": 0.002275,
        "overflow": 0
      },
      "Latency": {
        "count": 0,
        "min": 0,
        "max": 0,
        "mean": 0,
        "stdev": 0,
        "median": 0,
        "madev": 0,
        "overflow": 0
      },
      "Jitter": {
        "count": 0,
        "min": 0,
        "max": 0,
        "mean": 0,
        "stdev": 0,
        "median": 0,
        "madev": 0,
        "overflow": 0
      },
      "Round Trip Latency": {
        "count": 0,
        "min": 0,
        "max": 0,
        "mean": 0,
        "stdev": 0,
        "median": 0,
        "madev": 0,
        "overflow": 0
      },
      "Round Trip Jitter": {
        "count": 0,
        "min": 0,
        "max": 0,
        "mean": 0,
        "stdev": 0,
        "median": 0,
        "madev": 0,
        "overflow": 0
      }
    }
  },
  "echo_rtps": {
    "256": {
      "Errors": 0,
      "Max Discovery Time Delta": 0,
      "Discovery Time Delta": {
        "count": 0,
        "min": 0,
        "max": 0,
        "mean": 0,
        "stdev": 0,
        "median": 0,
        "madev": 0,
        "overflow": 0
      },
      "Cpu Utilization": {
        "count": 248,
        "min": 0,
        "max": 1.745636,
        "mean": 0.057467,
        "stdev": 0.175128,
        "median": 0,
        "madev": 0,
        "overflow": 0
      },
      "Memory Utilization": {
        "count": 248,
        "min": 0,
        "max": 1.439663,
        "mean": 1.422395,
        "stdev": 0.12841,
        "median": 1.429033,
        "madev": 0.01063,
        "overflow": 0
      },
      "Virtual Memory Utilization": {
        "count": 248,
        "min": 0,
        "max": 0.00225,
        "mean": 0.002041,
        "stdev": 0.000186,
        "median": 0.002059,
        "madev": 0,
        "overflow": 0
      },
      "Latency": {
        "count": 200,
        "min": 0.000502,
        "max": 0.00145,
        "mean": 0.000723,
        "stdev": 0.000065,
        "median": 0.000753,
        "madev": 0.000139,
        "overflow": 0
      },
      "Jitter": {
        "count": 198,
        "min": 0,
        "max": 0.000626,
        "mean": 0.00003,
        "stdev": 0.00006,
        "median": 0.000015,
        "madev": 0.000011,
        "overflow": 0
      },
      "Round Trip Latency": {
        "count": 100,
        "min": 0.000825,
        "max": 0.001309,
        "mean": 0.000901,
        "stdev": 0.000067,
        "median": 0.000888,
        "madev": 0.000019,
        "overflow": 0
      },
      "Round Trip Jitter": {
        "count": 99,
        "min": 0,
        "max": 0.000418,
        "mean": 0.00004,
        "stdev": 0.000067,
        "median": 0.000018,
        "madev": 0.000011,
        "overflow": 0
      }
    },
    "1024": {
      "Errors": 0,
      "Max Discovery Time Delta": 0,
      "Discovery Time Delta": {
        "count": 0,
        "min": 0,
        "max": 0,
        "mean": 0,
        "stdev": 0,
        "median": 0,
        "madev": 0,
        "overflow": 0
      },
      "Cpu Utilization": {
        "count": 248,
        "min": 0,
        "max": 1.503759,
        "mean": 0.053488,
        "stdev": 0.161828,
        "median": 0,
        "madev": 0,
        "overflow": 0
      },
      "Memory Utilization": {
        "count": 248,
        "min": 0,
        "max": 1.339532,
        "mean": 1.322244,
        "stdev": 0.119224,
        "median": 1.332942,
        "madev": 0.001913,
        "overflow": 0
      },
      "Virtual Memory Utilization": {
        "count": 248,
        "min": 0,
        "max": 0.00225,
        "mean": 0.002041,
        "stdev": 0.000186,
        "median": 0.002059,
        "madev": 0,
        "overflow": 0
      },
      "Latency": {
        "count": 200,
        "min": 0.000519,
        "max": 0.001395,
        "mean": 0.000692,
        "stdev": 0.000054,
        "median": 0.000697,
        "madev": 0.000054,
        "overflow": 0
      },
      "Jitter": {
        "count": 198,
        "min": 0,
        "max": 0.000645,
        "mean": 0.000025,
        "stdev": 0.000051,
        "median": 0.000013,
        "madev": 0.000009,
        "overflow": 0
      },
      "Round Trip Latency": {
        "count": 100,
        "min": 0.000786,
        "max": 0.001308,
        "mean": 0.000852,
        "stdev": 0.000052,
        "median": 0.00084,
        "madev": 0.000007,
        "overflow": 0
      },
      "Round Trip Jitter": {
        "count": 99,
        "min": 0,
        "max": 0.000451,
        "mean": 0.000021,
        "stdev": 0.000047,
        "median": 0.000009,
        "madev": 0.000008,
        "overflow": 0
      }
    },
    "4096": {
      "Errors": 0,
      "Max Discovery Time Delta": 0,
      "Discovery Time Delta": {
        "count": 0,
        "min": 0,
        "max": 0,
        "mean": 0,
        "stdev": 0,
        "median": 0,
        "madev": 0,
        "overflow": 0
      },
      "Cpu Utilization": {
        "count": 248,
        "min": 0,
        "max": 1.75,
        "mean": 0.054463,
        "stdev": 0.181201,
        "median": 0,
        "madev": 0,
        "overflow": 0
      },
      "Memory Utilization": {
        "count": 248,
        "min": 0,
        "max": 1.443064,
        "mean": 1.428925,
        "stdev": 0.129158,
        "median": 1.439663,
        "madev": 0.003401,
        "overflow": 0
      },
      "Virtual Memory Utilization": {
        "count": 248,
        "min": 0,
        "max": 0.00225,
        "mean": 0.002041,
        "stdev": 0.000186,
        "median": 0.002059,
        "madev": 0,
        "overflow": 0
      },
      "Latency": {
        "count": 200,
        "min": 0.00055,
        "max": 0.00102,
        "mean": 0.000791,
        "stdev": 0.000067,
        "median": 0.000813,
        "madev": 0.000111,
        "overflow": 0
      },
      "Jitter": {
        "count": 198,
        "min": 0,
        "max": 0.000179,
        "mean": 0.000028,
        "stdev": 0.000027,
        "median": 0.00002,
        "madev": 0.000012,
        "overflow": 0
      },
      "Round Trip Latency": {
        "count": 100,
        "min": 0.000854,
        "max": 0.001259,
        "mean": 0.000958,
        "stdev": 0.000048,
        "median": 0.000952,
        "madev": 0.000015,
        "overflow": 0
      },
      "Round Trip Jitter": {
        "count": 99,
        "min": 0,
        "max": 0.000405,
        "mean": 0.000034,
        "stdev": 0.000061,
        "median": 0.000018,
        "madev": 0.000012,
        "overflow": 0
      }
    },
    "16384": {
      "Errors": 0,
      "Max Discovery Time Delta": 0,
      "Discovery Time Delta": {
        "count": 0,
        "min": 0,
        "max": 0,
        "mean": 0,
        "stdev": 0,
        "median": 0,
        "madev": 0,
        "overflow": 0
      },
      "Cpu Utilization": {
        "count": 252,
        "min": 0,
        "max": 1.253133,
        "mean": 0.056623,
        "stdev": 0.152965,
        "median": 0,
        "madev": 0,
        "overflow": 0
      },
      "Memory Utilization": {
        "count": 252,
        "min": 0,
        "max": 1.526612,
        "mean": 1.413338,
        "stdev": 0.155431,
        "median": 1.435836,
        "madev": 0.010417,
        "overflow": 0
      },
      "Virtual Memory Utilization": {
        "count": 252,
        "min": 0,
        "max": 0.002251,
        "mean": 0.002038,
        "stdev": 0.000187,
        "median": 0.002059,
        "madev": 0,
        "overflow": 0
      },
      "Latency": {
        "count": 200,
        "min": 0.000746,
        "max": 0.001536,
        "mean": 0.000917,
        "stdev": 0.000059,
        "median": 0.000912,
        "madev": 0.000022,
        "overflow": 0
      },
      "Jitter": {
        "count": 198,
        "min": 0,
        "max": 0.00055,
        "mean": 0.000028,
        "stdev": 0.000053,
        "median": 0.000015,
        "madev": 0.000008,
        "overflow": 0
      },
      "Round Trip Latency": {
        "count": 100,
        "min": 0.000995,
        "max": 0.001566,
        "mean": 0.001084,
        "stdev": 0.000061,
        "median": 0.001086,
        "madev": 0.00002,
        "overflow": 0
      },
      "Round Trip Jitter": {
        "count": 99,
        "min": 0,
        "max": 0.000402,
        "mean": 0.000027,
        "stdev": 0.000053,
        "median": 0.000014,
        "madev": 0.000009,
        "overflow": 0
      }
    },
    "65536": {
      "Errors": 0,
      "Max Discovery Time Delta": 0,
      "Discovery Time Delta": {
        "count": 0,
        "min": 0,
        "max": 0,
        "mean": 0,
        "stdev": 0,
        "median": 0,
        "madev": 0,
        "overflow": 0
      },
      "Cpu Utilization": {
        "count": 248,
        "min": 0,
        "max": 1.754386,
        "mean": 0.076684,
        "stdev": 0.191175,
        "median": 0,
        "madev": 0,
        "overflow": 0
      },
      "Memory Utilization": {
        "count": 248,
        "min": 0,
        "max": 1.578272,
        "mean": 1.447025,
        "stdev": 0.140169,
        "median": 1.468362,
        "madev": 0.01063,
        "overflow": 0
      },
      "Virtual Memory Utilization": {
        "count": 248,
        "min": 0,
        "max": 0.002251,
        "mean": 0.002042,
        "stdev": 0.000186,
        "median": 0.002059,
        "madev": 0.000001,
        "overflow": 0
      },
      "Latency": {
        "count": 200,
        "min": 0.001392,
        "max": 0.002783,
        "mean": 0.00162,
        "stdev": 0.000144,
        "median": 0.001598,
        "madev": 0.000087,
        "overflow": 0
      },
      "Jitter": {
        "count": 198,
        "min": 0,
        "max": 0.001065,
        "mean": 0.000101,
        "stdev": 0.000105,
        "median": 0.000077,
        "madev": 0.000043,
        "overflow": 0
      },
      "Round Trip Latency": {
        "count": 100,
        "min": 0.001611,
        "max": 0.002818,
        "mean": 0.001792,
        "stdev": 0.000133,
        "median": 0.001781,
        "madev": 0.000061,
        "overflow": 0
      },
      "Round Trip Jitter": {
        "count": 99,
        "min": 0.000003,
        "max": 0.00093,
        "mean": 0.000091,
        "stdev": 0.000102,
        "median": 0.000073,
        "madev": 0.000041,
        "overflow": 0
      }
    },
    "262144": {
      "Errors": 0,
      "Max Discovery Time Delta": 0,
      "Discovery Time Delta": {
        "count": 0,
        "min": 0,
        "max": 0,
        "mean": 0,
        "stdev": 0,
        "median": 0,
        "madev": 0,
        "overflow": 0
      },
      "Cpu Utilization": {
        "count": 252,
        "min": 0,
        "max": 1.503759,
        "mean": 0.185765,
        "stdev": 0.19462,
        "median": 0.25,
        "madev": 0.25,
        "overflow": 0
      },
      "Memory Utilization": {
        "count": 252,
        "min": 0,
        "max": 1.69796,
        "mean": 1.59341,
        "stdev": 0.183316,
        "median": 1.612499,
        "madev": 0.052297,
        "overflow": 0
      },
      "Virtual Memory Utilization": {
        "count": 252,
        "min": 0,
        "max": 0.002252,
        "mean": 0.002039,
        "stdev": 0.000187,
        "median": 0.002059,
        "madev": 0.000002,
        "overflow": 0
      },
      "Latency": {
        "count": 200,
        "min": 0.004003,
        "max": 0.007284,
        "mean": 0.004747,
        "stdev": 0.000376,
        "median": 0.00476,
        "madev": 0.000253,
        "overflow": 0
      },
      "Jitter": {
        "count": 198,
        "min": 0.000005,
        "max": 0.002346,
        "mean": 0.000288,
        "stdev": 0.000302,
        "median": 0.000123,
        "madev": 0.000087,
        "overflow": 0
      },
      "Round Trip Latency": {
        "count": 100,
        "min": 0.004589,
        "max": 0.007461,
        "mean": 0.004951,
        "stdev": 0.000344,
        "median": 0.004875,
        "madev": 0.000201,
        "overflow": 0
      },
      "Round Trip Jitter": {
        "count": 99,
        "min": 0.000003,
        "max": 0.002111,
        "mean": 0.000257,
        "stdev": 0.000258,
        "median": 0.000203,
        "madev": 0.000157,
        "overflow": 0
      }
    },
    "1048576": {
      "Errors": 0,
      "Max Discovery Time Delta": 0,
      "Discovery Time Delta": {
        "count": 0,
        "min": 0,
        "max": 0,
        "mean": 0,
        "stdev": 0,
        "median": 0,
        "madev": 0,
        "overflow": 0
      },
      "Cpu Utilization": {
        "count": 248,
        "min": 0,
        "max": 2.267003,
        "mean": 1.267486,
        "stdev": 0.660112,
        "median": 1.503759,
        "madev": 0.255035,
        "overflow": 0
      },
      "Memory Utilization": {
        "count": 248,
        "min": 0,
        "max": 3.343835,
        "mean": 2.144528,
        "stdev": 0.448933,
        "median": 1.880788,
        "madev": 0.161144,
        "overflow": 0
      },
      "Virtual Memory Utilization": {
        "count": 248,
        "min": 0,
        "max": 0.002256,
        "mean": 0.002044,
        "stdev": 0.000187,
        "median": 0.002059,
        "madev": 0.000006,
        "overflow": 0
      },
      "Latency": {
        "count": 200,
        "min": 0.016323,
        "max": 0.0633,
        "mean": 0.046726,
        "stdev": 0.008136,
        "median": 0.054878,
        "madev": 0.003366,
        "overflow": 0
      },
      "Jitter": {
        "count": 198,
        "min": 0.000005,
        "max": 0.030386,
        "mean": 0.002684,
        "stdev": 0.005139,
        "median": 0.000388,
        "madev": 0.000341,
        "overflow": 0
      },
      "Round Trip Latency": {
        "count": 100,
        "min": 0.03735,
        "max": 0.063412,
        "mean": 0.047016,
        "stdev": 0.005863,
        "median": 0.047103,
        "madev": 0.004701,
        "overflow": 0
      },
      "Round Trip Jitter": {
        "count": 99,
        "min": 0.000006,
        "max": 0.015445,
        "mean": 0.00254,
        "stdev": 0.003664,
        "median": 0.001367,
        "madev": 0.00101,
        "overflow": 0
      }
    },
    "4194304": {
      "Errors": 0,
      "Max Discovery Time Delta": 0,
      "Discovery Time Delta": {
        "count": 0,
        "min": 0,
        "max": 0,
        "mean": 0,
        "stdev": 0,
        "median": 0,
        "madev": 0,
        "overflow": 0
      },
      "Cpu Utilization": {
        "count": 252,
        "min": 0,
        "max": 25.822785,
        "mean": 10.683089,
        "stdev": 5.904843,
        "median": 12.468193,
        "madev": 2.563678,
        "overflow": 0
      },
      "Memory Utilization": {
        "count": 252,
        "min": 0,
        "max": 61.022815,
        "mean": 31.074821,
        "stdev": 16.034729,
        "median": 30.573697,
        "madev": 6.752192,
        "overflow": 0
      },
      "Virtual Memory Utilization": {
        "count": 252,
        "min": 0,
        "max": 0.005302,
        "mean": 0.003616,
        "stdev": 0.000964,
        "median": 0.003609,
        "madev": 0.000405,
        "overflow": 0
      },
      "Latency": {
        "count": 200,
        "min": 0.2779,
        "max": 0.737185,
        "mean": 0.473232,
        "stdev": 0.09998,
        "median": 0.497504,
        "madev": 0.084026,
        "overflow": 0
      },
      "Jitter": {
        "count": 198,
        "min": 0.000122,
        "max": 0.320522,
        "mean": 0.106288,
        "stdev": 0.083588,
        "median": 0.083533,
        "madev": 0.066398,
        "overflow": 0
      },
      "Round Trip Latency": {
        "count": 100,
        "min": 0.302137,
        "max": 0.717965,
        "mean": 0.474194,
        "stdev": 0.069692,
        "median": 0.473038,
        "madev": 0.040693,
        "overflow": 0
      },
      "Round Trip Jitter": {
        "count": 99,
        "min": 0.00012,
        "max": 0.272997,
        "mean": 0.08707,
        "stdev": 0.063978,
        "median": 0.062894,
        "madev": 0.034763,
        "overflow": 0
      }
    }
  },
  "echo_tcp": {
    "256": {
      "Errors": 0,
      "Max Discovery Time Delta": 0,
      "Discovery Time Delta": {
        "count": 0,
        "min": 0,
        "max": 0,
        "mean": 0,
        "stdev": 0,
        "median": 0,
        "madev": 0,
        "overflow": 0
      },
      "Cpu Utilization": {
        "count": 248,
        "min": 0,
        "max": 1.758794,
        "mean": 0.038375,
        "stdev": 0.171661,
        "median": 0,
        "madev": 0,
        "overflow": 0
      },
      "Memory Utilization": {
        "count": 248,
        "min": 0,
        "max": 1.808932,
        "mean": 1.620122,
        "stdev": 0.160077,
        "median": 1.602294,
        "madev": 0.006165,
        "overflow": 0
      },
      "Virtual Memory Utilization": {
        "count": 248,
        "min": 0,
        "max": 0.002288,
        "mean": 0.002079,
        "stdev": 0.00019,
        "median": 0.002097,
        "madev": 0,
        "overflow": 0
      },
      "Latency": {
        "count": 200,
        "min": 0.000368,
        "max": 0.001224,
        "mean": 0.000548,
        "stdev": 0.000084,
        "median": 0.000536,
        "madev": 0.000039,
        "overflow": 0
      },
      "Jitter": {
        "count": 198,
        "min": 0,
        "max": 0.0005,
        "mean": 0.000017,
        "stdev": 0.000041,
        "median": 0.000009,
        "madev": 0.000006,
        "overflow": 0
      },
      "Round Trip Latency": {
        "count": 100,
        "min": 0.000667,
        "max": 0.00117,
        "mean": 0.000737,
        "stdev": 0.000046,
        "median": 0.000731,
        "madev": 0.000011,
        "overflow": 0
      },
      "Round Trip Jitter": {
        "count": 99,
        "min": 0.000001,
        "max": 0.000437,
        "mean": 0.000016,
        "stdev": 0.000045,
        "median": 0.000008,
        "madev": 0.000004,
        "overflow": 0
      }
    },
    "1024": {
      "Errors": 0,
      "Max Discovery Time Delta": 0,
      "Discovery Time Delta": {
        "count": 0,
        "min": 0,
        "max": 0,
        "mean": 0,
        "stdev": 0,
        "median": 0,
        "madev": 0,
        "overflow": 0
      },
      "Cpu Utilization": {
        "count": 248,
        "min": 0,
        "max": 2.01005,
        "mean": 0.037377,
        "stdev": 0.18127,
        "median": 0,
        "madev": 0,
        "overflow": 0
      },
      "Memory Utilization": {
        "count": 248,
        "min": 0,
        "max": 1.710503,
        "mean": 1.650075,
        "stdev": 0.152216,
        "median": 1.688819,
        "madev": 0.021684,
        "overflow": 0
      },
      "Virtual Memory Utilization": {
        "count": 248,
        "min": 0,
        "max": 0.002288,
        "mean": 0.002078,
        "stdev": 0.000189,
        "median": 0.002097,
        "madev": 0,
        "overflow": 0
      },
      "Latency": {
        "count": 200,
        "min": 0.000392,
        "max": 0.000999,
        "mean": 0.000536,
        "stdev": 0.000041,
        "median": 0.000559,
        "madev": 0.000065,
        "overflow": 0
      },
      "Jitter": {
        "count": 198,
        "min": 0,
        "max": 0.000512,
        "mean": 0.000021,
        "stdev": 0.000039,
        "median": 0.000012,
        "madev": 0.000009,
        "overflow": 0
      },
      "Round Trip Latency": {
        "count": 100,
        "min": 0.00067,
        "max": 0.001103,
        "mean": 0.000707,
        "stdev": 0.000045,
        "median": 0.000706,
        "madev": 0.00002,
        "overflow": 0
      },
      "Round Trip Jitter": {
        "count": 99,
        "min": 0,
        "max": 0.000385,
        "mean": 0.000023,
        "stdev": 0.000039,
        "median": 0.000017,
        "madev": 0.000011,
        "overflow": 0
      }
    },
    "4096": {
      "Errors": 0,
      "Max Discovery Time Delta": 0,
      "Discovery Time Delta": {
        "count": 0,
        "min": 0,
        "max": 0,
        "mean": 0,
        "stdev": 0,
        "median": 0,
        "madev": 0,
        "overflow": 0
      },
      "Cpu Utilization": {
        "count": 252,
        "min": 0,
        "max": 1.503759,
        "mean": 0.038725,
        "stdev": 0.14873,
        "median": 0,
        "madev": 0,
        "overflow": 0
      },
      "Memory Utilization": {
        "count": 252,
        "min": 0,
        "max": 1.70455,
        "mean": 1.588455,
        "stdev": 0.175994,
        "median": 1.597617,
        "madev": 0.004039,
        "overflow": 0
      },
      "Virtual Memory Utilization": {
        "count": 252,
        "min": 0,
        "max": 0.002288,
        "mean": 0.002075,
        "stdev": 0.000191,
        "median": 0.002097,
        "madev": 0,
        "overflow": 0
      },
      "Latency": {
        "count": 200,
        "min": 0.000462,
        "max": 0.001142,
        "mean": 0.000596,
        "stdev": 0.000087,
        "median": 0.000555,
        "madev": 0.000027,
        "overflow": 0
      },
      "Jitter": {
        "count": 198,
        "min": 0,
        "max": 0.000573,
        "mean": 0.000047,
        "stdev": 0.000085,
        "median": 0.000013,
        "madev": 0.000012,
        "overflow": 0
      },
      "Round Trip Latency": {
        "count": 100,
        "min": 0.000719,
        "max": 0.001302,
        "mean": 0.000782,
        "stdev": 0.000077,
        "median": 0.000764,
        "madev": 0.00002,
        "overflow": 0
      },
      "Round Trip Jitter": {
        "count": 99,
        "min": 0,
        "max": 0.000511,
        "mean": 0.000045,
        "stdev": 0.00007,
        "median": 0.000025,
        "madev": 0.000017,
        "overflow": 0
      }
    },
    "16384": {
      "Errors": 0,
      "Max Discovery Time Delta": 0,
      "Discovery Time Delta": {
        "count": 0,
        "min": 0,
        "max": 0,
        "mean": 0,
        "stdev": 0,
        "median": 0,
        "madev": 0,
        "overflow": 0
      },
      "Cpu Utilization": {
        "count": 252,
        "min": 0,
        "max": 1.75,
        "mean": 0.040714,
        "stdev": 0.162556,
        "median": 0,
        "madev": 0,
        "overflow": 0
      },
      "Memory Utilization": {
        "count": 252,
        "min": 0,
        "max": 1.911613,
        "mean": 1.751296,
        "stdev": 0.199965,
        "median": 1.754296,
        "madev": 0.028062,
        "overflow": 0
      },
      "Virtual Memory Utilization": {
        "count": 252,
        "min": 0,
        "max": 0.002289,
        "mean": 0.002075,
        "stdev": 0.000191,
        "median": 0.002097,
        "madev": 0,
        "overflow": 0
      },
      "Latency": {
        "count": 200,
        "min": 0.000647,
        "max": 0.001322,
        "mean": 0.001004,
        "stdev": 0.00015,
        "median": 0.001005,
        "madev": 0.000134,
        "overflow": 0
      },
      "Jitter": {
        "count": 198,
        "min": 0,
        "max": 0.000632,
        "mean": 0.000108,
        "stdev": 0.000104,
        "median": 0.000075,
        "madev": 0.00006,
        "overflow": 0
      },
      "Round Trip Latency": {
        "count": 100,
        "min": 0.000876,
        "max": 0.001562,
        "mean": 0.00118,
        "stdev": 0.000131,
        "median": 0.001167,
        "madev": 0.000107,
        "overflow": 0
      },
      "Round Trip Jitter": {
        "count": 99,
        "min": 0.000001,
        "max": 0.000333,
        "mean": 0.000092,
        "stdev": 0.000073,
        "median": 0.000079,
        "madev": 0.000048,
        "overflow": 0
      }
    },
    "65536": {
      "Errors": 0,
      "Max Discovery Time Delta": 0,
      "Discovery Time Delta": {
        "count": 0,
        "min": 0,
        "max": 0,
        "mean": 0,
        "stdev": 0,
        "median": 0,
        "madev": 0,
        "overflow": 0
      },
      "Cpu Utilization": {
        "count": 248,
        "min": 0,
        "max": 2.005013,
        "mean": 0.045401,
        "stdev": 0.188621,
        "median": 0,
        "madev": 0,
        "overflow": 0
      },
      "Memory Utilization": {
        "count": 248,
        "min": 0,
        "max": 1.840396,
        "mean": 1.734365,
        "stdev": 0.164152,
        "median": 1.781189,
        "madev": 0.052404,
        "overflow": 0
      },
      "Virtual Memory Utilization": {
        "count": 248,
        "min": 0,
        "max": 0.002289,
        "mean": 0.002079,
        "stdev": 0.00019,
        "median": 0.002097,
        "madev": 0,
        "overflow": 0
      },
      "Latency": {
        "count": 200,
        "min": 0.00099,
        "max": 0.002,
        "mean": 0.00134,
        "stdev": 0.000132,
        "median": 0.001342,
        "madev": 0.00007,
        "overflow": 0
      },
      "Jitter": {
        "count": 198,
        "min": 0.000001,
        "max": 0.000612,
        "mean": 0.000109,
        "stdev": 0.000106,
        "median": 0.000075,
        "madev": 0.00005,
        "overflow": 0
      },
      "Round Trip Latency": {
        "count": 100,
        "min": 0.001255,
        "max": 0.002276,
        "mean": 0.001536,
        "stdev": 0.000123,
        "median": 0.001544,
        "madev": 0.000066,
        "overflow": 0
      },
      "Round Trip Jitter": {
        "count": 99,
        "min": 0.000002,
        "max": 0.00072,
        "mean": 0.000089,
        "stdev": 0.000102,
        "median": 0.000055,
        "madev": 0.000036,
        "overflow": 0
      }
    },
    "262144": {
      "Errors": 0,
      "Max Discovery Time Delta": 0,
      "Discovery Time Delta": {
        "count": 0,
        "min": 0,
        "max": 0,
        "mean": 0,
        "stdev": 0,
        "median": 0,
        "madev": 0,
        "overflow": 0
      },
      "Cpu Utilization": {
        "count": 248,
        "min": 0,
        "max": 1.754386,
        "mean": 0.079718,
        "stdev": 0.190401,
        "median": 0,
        "madev": 0,
        "overflow": 0
      },
      "Memory Utilization": {
        "count": 248,
        "min": 0,
        "max": 1.994949,
        "mean": 1.801813,
        "stdev": 0.171149,
        "median": 1.854852,
        "madev": 0.038054,
        "overflow": 0
      },
      "Virtual Memory Utilization": {
        "count": 248,
        "min": 0,
        "max": 0.00229,
        "mean": 0.00208,
        "stdev": 0.00019,
        "median": 0.002097,
        "madev": 0.000002,
        "overflow": 0
      },
      "Latency": {
        "count": 200,
        "min": 0.002229,
        "max": 0.005257,
        "mean": 0.003269,
        "stdev": 0.000494,
        "median": 0.003196,
        "madev": 0.000245,
        "overflow": 0
      },
      "Jitter": {
        "count": 198,
        "min": 0.000001,
        "max": 0.001885,
        "mean": 0.000485,
        "stdev": 0.000437,
        "median": 0.000402,
        "madev": 0.000329,
        "overflow": 0
      },
      "Round Trip Latency": {
        "count": 100,
        "min": 0.002878,
        "max": 0.005409,
        "mean": 0.003474,
        "stdev": 0.000364,
        "median": 0.003486,
        "madev": 0.000225,
        "overflow": 0
      },
      "Round Trip Jitter": {
        "count": 99,
        "min": 0,
        "max": 0.001689,
        "mean": 0.000375,
        "stdev": 0.000269,
        "median": 0.000354,
        "madev": 0.000172,
        "overflow": 0
      }
    },
    "1048576": {
      "Errors": 0,
      "Max Discovery Time Delta": 0,
      "Discovery Time Delta": {
        "count": 0,
        "min": 0,
        "max": 0,
        "mean": 0,
        "stdev": 0,
        "median": 0,
        "madev": 0,
        "overflow": 0
      },
      "Cpu Utilization": {
        "count": 248,
        "min": 0,
        "max": 1.758794,
        "mean": 0.21201,
        "stdev": 0.219813,
        "median": 0.25,
        "madev": 0.125005,
        "overflow": 0
      },
      "Memory Utilization": {
        "count": 248,
        "min": 0,
        "max": 2.193721,
        "mean": 1.956942,
        "stdev": 0.194116,
        "median": 1.937762,
        "madev": 0.137971,
        "overflow": 0
      },
      "Virtual Memory Utilization": {
        "count": 248,
        "min": 0,
        "max": 0.002294,
        "mean": 0.002082,
        "stdev": 0.00019,
        "median": 0.002097,
        "madev": 0.000006,
        "overflow": 0
      },
      "Latency": {
        "count": 200,
        "min": 0.006918,
        "max": 0.018056,
        "mean": 0.009637,
        "stdev": 0.001392,
        "median": 0.010217,
        "madev": 0.000933,
        "overflow": 0
      },
      "Jitter": {
        "count": 198,
        "min": 0.000003,
        "max": 0.007472,
        "mean": 0.001226,
        "stdev": 0.001336,
        "median": 0.000462,
        "madev": 0.000353,
        "overflow": 0
      },
      "Round Trip Latency": {
        "count": 100,
        "min": 0.008544,
        "max": 0.017044,
        "mean": 0.009949,
        "stdev": 0.001115,
        "median": 0.00962,
        "madev": 0.000424,
        "overflow": 0
      },
      "Round Trip Jitter": {
        "count": 99,
        "min": 0.000011,
        "max": 0.005613,
        "mean": 0.001071,
        "stdev": 0.000974,
        "median": 0.000721,
        "madev": 0.000613,
        "overflow": 0
      }
    },
    "4194304": {
      "Errors": 0,
      "Max Discovery Time Delta": 0,
      "Discovery Time Delta": {
        "count": 0,
        "min": 0,
        "max": 0,
        "mean": 0,
        "stdev": 0,
        "median": 0,
        "madev": 0,
        "overflow": 0
      },
      "Cpu Utilization": {
        "count": 252,
        "min": 0,
        "max": 1.5,
        "mean": 0.654344,
        "stdev": 0.35954,
        "median": 0.75188,
        "madev": 0.250627,
        "overflow": 0
      },
      "Memory Utilization": {
        "count": 252,
        "min": 0,
        "max": 3.853627,
        "mean": 2.809317,
        "stdev": 0.470097,
        "median": 2.248357,
        "madev": 0.842921,
        "overflow": 0
      },
      "Virtual Memory Utilization": {
        "count": 252,
        "min": 0,
        "max": 0.002312,
        "mean": 0.002087,
        "stdev": 0.000192,
        "median": 0.002097,
        "madev": 0.000024,
        "overflow": 0
      },
      "Latency": {
        "count": 200,
        "min": 0.024532,
        "max": 0.048792,
        "mean": 0.033293,
        "stdev": 0.002552,
        "median": 0.034921,
        "madev": 0.001341,
        "overflow": 0
      },
      "Jitter": {
        "count": 198,
        "min": 0.000003,
        "max": 0.012241,
        "mean": 0.002218,
        "stdev": 0.002648,
        "median": 0.000662,
        "madev": 0.000451,
        "overflow": 0
      },
      "Round Trip Latency": {
        "count": 100,
        "min": 0.027618,
        "max": 0.046526,
        "mean": 0.034301,
        "stdev": 0.002096,
        "median": 0.033451,
        "madev": 0.000457,
        "overflow": 0
      },
      "Round Trip Jitter": {
        "count": 99,
        "min": 0.000015,
        "max": 0.00859,
        "mean": 0.002056,
        "stdev": 0.001787,
        "median": 0.002277,
        "madev": 0.001658,
        "overflow": 0
      }
    }
  },
  "fan_rtps": {
    "256_4": {
      "Errors": 0,
      "Max Discovery Time Delta": 3.208205,
      "Discovery Time Delta": {
        "count": 6,
        "min": 3.117007,
        "max": 3.208205,
        "mean": 3.191379,
        "stdev": 0.030365,
        "median": 3.205094,
        "madev": 0.001559,
        "overflow": 0
      },
      "Cpu Utilization": {
        "count": 330,
        "min": 0,
        "max": 1.5,
        "mean": 0.050796,
        "stdev": 0.199087,
        "median": 0,
        "madev": 0,
        "overflow": 0
      },
      "Memory Utilization": {
        "count": 330,
        "min": 0,
        "max": 1.443277,
        "mean": 1.316573,
        "stdev": 0.175872,
        "median": 1.331029,
        "madev": 0.000213,
        "overflow": 0
      },
      "Virtual Memory Utilization": {
        "count": 330,
        "min": 0,
        "max": 0.00225,
        "mean": 0.002019,
        "stdev": 0.000256,
        "median": 0.002059,
        "madev": 0,
        "overflow": 0
      },
      "Latency": {
        "count": 80,
        "min": 0.000554,
        "max": 0.001847,
        "mean": 0.000877,
        "stdev": 0.000221,
        "median": 0.000824,
        "madev": 0.000105,
        "overflow": 0
      },
      "Jitter": {
        "count": 72,
        "min": 0,
        "max": 0.000973,
        "mean": 0.00014,
        "stdev": 0.000187,
        "median": 0.00006,
        "madev": 0.000052,
        "overflow": 0
      },
      "Round Trip Latency": {
        "count": 40,
        "min": 0.000825,
        "max": 0.001781,
        "mean": 0.00104,
        "stdev": 0.000217,
        "median": 0.000987,
        "madev": 0.000086,
        "overflow": 0
      },
      "Round Trip Jitter": {
        "count": 36,
        "min": 0.00001,
        "max": 0.000704,
        "mean": 0.000116,
        "stdev": 0.000191,
        "median": 0.000026,
        "madev": 0.000011,
        "overflow": 0
      }
    },
    "256_16": {
      "Errors": 0,
      "Max Discovery Time Delta": 3.225735,
      "Discovery Time Delta": {
        "count": 30,
        "min": 0.20754,
        "max": 3.225735,
        "mean": 3.012909,
        "stdev": 0.749342,
        "median": 3.209482,
        "madev": 0.003011,
        "overflow": 0
      },
      "Cpu Utilization": {
        "count": 1120,
        "min": 0,
        "max": 2.261307,
        "mean": 0.074451,
        "stdev": 0.300371,
        "median": 0,
        "madev": 0,
        "overflow": 0
      },
      "Memory Utilization": {
        "count": 1120,
        "min": 0,
        "max": 1.461347,
        "mean": 1.350691,
        "stdev": 0.177721,
        "median": 1.34506,
        "madev": 0.102043,
        "overflow": 0
      },
      "Virtual Memory Utilization": {
        "count": 1120,
        "min": 0,
        "max": 0.00225,
        "mean": 0.002019,
        "stdev": 0.000256,
        "median": 0.002059,
        "madev": 0,
        "overflow": 0
      },
      "Latency": {
        "count": 320,
        "min": 0.000583,
        "max": 0.005189,
        "mean": 0.001383,
        "stdev": 0.000667,
        "median": 0.000965,
        "madev": 0.000279,
        "overflow": 0
      },
      "Jitter": {
        "count": 288,
        "min": 0,
        "max": 0.00399,
        "mean": 0.000255,
        "stdev": 0.000542,
        "median": 0.00005,
        "madev": 0.000045,
        "overflow": 0
      },
      "Round Trip Latency": {
        "count": 160,
        "min": 0.000827,
        "max": 0.003478,
        "mean": 0.001559,
        "stdev": 0.000553,
        "median": 0.001478,
        "madev": 0.000302,
        "overflow": 0
      },
      "Round Trip Jitter": {
        "count": 144,
        "min": 0.000001,
        "max": 0.002386,
        "mean": 0.000261,
        "stdev": 0.00045,
        "median": 0.000109,
        "madev": 0.000081,
        "overflow": 0
      }
    },
    "4096_4": {
      "Errors": 0,
      "Max Discovery Time Delta": 3.303348,
      "Discovery Time Delta": {
        "count": 6,
        "min": 0.206359,
        "max": 3.303348,
        "mean": 2.22261,
        "stdev": 1.42368,
        "median": 3.203582,
        "madev": 0.050937,
        "overflow": 0
      },
      "Cpu Utilization": {
        "count": 332,
        "min": 0,
        "max": 2,
        "mean": 0.049725,
        "stdev": 0.229101,
        "median": 0,
        "madev": 0,
        "overflow": 0
      },
      "Memory Utilization": {
        "count": 332,
        "min": 0,
        "max": 1.547659,
        "mean": 1.376573,
        "stdev": 0.178515,
        "median": 1.426269,
        "madev": 0.091414,
        "overflow": 0
      },
      "Virtual Memory Utilization": {
        "count": 332,
        "min": 0,
        "max": 0.00225,
        "mean": 0.002018,
        "stdev": 0.000257,
        "median": 0.002059,
        "madev": 0,
        "overflow": 0
      },
      "Latency": {
        "count": 80,
        "min": 0.000721,
        "max": 0.002902,
        "mean": 0.001,
        "stdev": 0.000329,
        "median": 0.00093,
        "madev": 0.000131,
        "overflow": 0
      },
      "Jitter": {
        "count": 72,
        "min": 0.000002,
        "max": 0.001793,
        "mean": 0.00015,
        "stdev": 0.000321,
        "median": 0.000041,
        "madev": 0.000033,
        "overflow": 0
      },
      "Round Trip Latency": {
        "count": 40,
        "min": 0.000885,
        "max": 0.002214,
        "mean": 0.001166,
        "stdev": 0.000309,
        "median": 0.001093,
        "madev": 0.000111,
        "overflow": 0
      },
      "Round Trip Jitter": {
        "count": 36,
        "min": 0.000006,
        "max": 0.000937,
        "mean": 0.00015,
        "stdev": 0.000269,
        "median": 0.000031,
        "madev": 0.000017,
        "overflow": 0
      }
    },
    "4096_16": {
      "Errors": 0,
      "Max Discovery Time Delta": 3.22405,
      "Discovery Time Delta": {
        "count": 30,
        "min": 0.205374,
        "max": 3.22405,
        "mean": 2.612468,
        "stdev": 1.20153,
        "median": 3.207299,
        "madev": 0.011219,
        "overflow": 0
      },
      "Cpu Utilization": {
        "count": 1116,
        "min": 0,
        "max": 2.506266,
        "mean": 0.076517,
        "stdev": 0.310385,
        "median": 0,
        "madev": 0,
        "overflow": 0
      },
      "Memory Utilization": {
        "count": 1116,
        "min": 0,
        "max": 1.560627,
        "mean": 1.371468,
        "stdev": 0.179307,
        "median": 1.354308,
        "madev": 0.086843,
        "overflow": 0
      },
      "Virtual Memory Utilization": {
        "count": 1116,
        "min": 0,
        "max": 0.00225,
        "mean": 0.002018,
        "stdev": 0.000257,
        "median": 0.002059,
        "madev": 0,
        "overflow": 0
      },
      "Latency": {
        "count": 320,
        "min": 0.000644,
        "max": 0.00546,
        "mean": 0.001496,
        "stdev": 0.000708,
        "median": 0.001144,
        "madev": 0.000261,
        "overflow": 0
      },
      "Jitter": {
        "count": 288,
        "min": 0,
        "max": 0.004023,
        "mean": 0.000356,
        "stdev": 0.000665,
        "median": 0.000101,
        "madev": 0.000086,
        "overflow": 0
      },
      "Round Trip Latency": {
        "count": 160,
        "min": 0.000911,
        "max": 0.003712,
        "mean": 0.001662,
        "stdev": 0.00058,
        "median": 0.001572,
        "madev": 0.000343,
        "overflow": 0
      },
      "Round Trip Jitter": {
        "count": 144,
        "min": 0,
        "max": 0.002279,
        "mean": 0.000342,
        "stdev": 0.000528,
        "median": 0.000149,
        "madev": 0.000132,
        "overflow": 0
      }
    },
    "65536_4": {
      "Errors": 0,
      "Max Discovery Time Delta": 3.205944,
      "Discovery Time Delta": {
        "count": 6,
        "min": 0.205882,
        "max": 3.205944,
        "mean": 2.206725,
        "stdev": 1.412556,
        "median": 3.205227,
        "madev": 0.00065,
        "overflow": 0
      },
      "Cpu Utilization": {
        "count": 332,
        "min": 0,
        "max": 1.754386,
        "mean": 0.056603,
        "stdev": 0.214875,
        "median": 0,
        "madev": 0,
        "overflow": 0
      },
      "Memory Utilization": {
        "count": 332,
        "min": 0,
        "max": 1.586775,
        "mean": 1.389925,
        "stdev": 0.181484,
        "median": 1.378862,
        "madev": 0.006165,
        "overflow": 0
      },
      "Virtual Memory Utilization": {
        "count": 332,
        "min": 0,
        "max": 0.002251,
        "mean": 0.002018,
        "stdev": 0.000257,
        "median": 0.002059,
        "madev": 0,
        "overflow": 0
      },
      "Latency": {
        "count": 80,
        "min": 0.001389,
        "max": 0.00656,
        "mean": 0.003548,
        "stdev": 0.00126,
        "median": 0.003789,
        "madev": 0.0017,
        "overflow": 0
      },
      "Jitter": {
        "count": 72,
        "min": 0.000008,
        "max": 0.001701,
        "mean": 0.000297,
        "stdev": 0.000286,
        "median": 0.000176,
        "madev": 0.000116,
        "overflow": 0
      },
      "Round Trip Latency": {
        "count": 40,
        "min": 0.001737,
        "max": 0.006107,
        "mean": 0.003722,
        "stdev": 0.001691,
        "median": 0.003994,
        "madev": 0.001843,
        "overflow": 0
      },
      "Round Trip Jitter": {
        "count": 36,
        "min": 0.000024,
        "max": 0.001157,
        "mean": 0.000247,
        "stdev": 0.000239,
        "median": 0.000176,
        "madev": 0.000129,
        "overflow": 0
      }
    },
    "65536_16": {
      "Errors": 0,
      "Max Discovery Time Delta": 3.225357,
      "Discovery Time Delta": {
        "count": 30,
        "min": 0.219476,
        "max": 3.225357,
        "mean": 1.020748,
        "stdev": 1.321964,
        "median": 0.226733,
        "madev": 0.006607,
        "overflow": 0
      },
      "Cpu Utilization": {
        "count": 1100,
        "min": 0,
        "max": 3.25,
        "mean": 0.091101,
        "stdev": 0.359282,
        "median": 0,
        "madev": 0,
        "overflow": 0
      },
      "Memory Utilization": {
        "count": 1100,
        "min": 0,
        "max": 1.60357,
        "mean": 1.40146,
        "stdev": 0.182988,
        "median": 1.395444,
        "madev": 0.006165,
        "overflow": 0
      },
      "Virtual Memory Utilization": {
        "count": 1100,
        "min": 0,
        "max": 0.002251,
        "mean": 0.002019,
        "stdev": 0.000258,
        "median": 0.002059,
        "madev": 0,
        "overflow": 0
      },
      "Latency": {
        "count": 320,
        "min": 0.001465,
        "max": 0.013945,
        "mean": 0.004547,
        "stdev": 0.002064,
        "median": 0.004366,
        "madev": 0.001285,
        "overflow": 0
      },
      "Jitter": {
        "count": 288,
        "min": 0,
        "max": 0.006338,
        "mean": 0.000613,
        "stdev": 0.000886,
        "median": 0.000256,
        "madev": 0.000208,
        "overflow": 0
      },
      "Round Trip Latency": {
        "count": 160,
        "min": 0.001901,
        "max": 0.009746,
        "mean": 0.004754,
        "stdev": 0.00202,
        "median": 0.004789,
        "madev": 0.001131,
        "overflow": 0
      },
      "Round Trip Jitter": {
        "count": 144,
        "min": 0.000004,
        "max": 0.004235,
        "mean": 0.000557,
        "stdev": 0.00072,
        "median": 0.000291,
        "madev": 0.000168,
        "overflow": 0
      }
    },
    "1048576_4": {
      "Errors": 0,
      "Max Discovery Time Delta": 3.214729,
      "Discovery Time Delta": {
        "count": 6,
        "min": 3.208653,
        "max": 3.214729,
        "mean": 3.211477,
        "stdev": 0.000347,
        "median": 3.211319,
        "madev": 0.00257,
        "overflow": 0
      },
      "Cpu Utilization": {
        "count": 330,
        "min": 0,
        "max": 2.531646,
        "mean": 0.358707,
        "stdev": 0.773562,
        "median": 0,
        "madev": 0,
        "overflow": 0
      },
      "Memory Utilization": {
        "count": 330,
        "min": 0,
        "max": 3.885091,
        "mean": 2.147664,
        "stdev": 0.698063,
        "median": 1.885252,
        "madev": 0.150301,
        "overflow": 0
      },
      "Virtual Memory Utilization": {
        "count": 330,
        "min": 0,
        "max": 0.002256,
        "mean": 0.00202,
        "stdev": 0.000256,
        "median": 0.002059,
        "madev": 0,
        "overflow": 0
      },
      "Latency": {
        "count": 80,
        "min": 0.026785,
        "max": 0.078262,
        "mean": 0.054249,
        "stdev": 0.007594,
        "median": 0.057373,
        "madev": 0.00498,
        "overflow": 0
      },
      "Jitter": {
        "count": 72,
        "min": 0.000011,
        "max": 0.026316,
        "mean": 0.003677,
        "stdev": 0.004933,
        "median": 0.002161,
        "madev": 0.001901,
        "overflow": 0
      },
      "Round Trip Latency": {
        "count": 40,
        "min": 0.042064,
        "max": 0.069764,
        "mean": 0.054624,
        "stdev": 0.007162,
        "median": 0.054649,
        "madev": 0.005615,
        "overflow": 0
      },
      "Round Trip Jitter": {
        "count": 36,
        "min": 0.000017,
        "max": 0.013611,
        "mean": 0.003413,
        "stdev": 0.003469,
        "median": 0.001962,
        "madev": 0.001867,
        "overflow": 0
      }
    },
    "1048576_16": {
      "Errors": 0,
      "Max Discovery Time Delta": 3.231193,
      "Discovery Time Delta": {
        "count": 30,
        "min": 0.20986,
        "max": 3.231193,
        "mean": 2.414535,
        "stdev": 1.328017,
        "median": 3.207327,
        "madev": 0.014806,
        "overflow": 0
      },
      "Cpu Utilization": {
        "count": 1114,
        "min": 0,
        "max": 3.856041,
        "mean": 0.479292,
        "stdev": 0.927067,
        "median": 0,
        "madev": 0,
        "overflow": 0
      },
      "Memory Utilization": {
        "count": 1114,
        "min": 0,
        "max": 21.059423,
        "mean": 10.290754,
        "stdev": 5.161007,
        "median": 6.621768,
        "madev": 5.168287,
        "overflow": 0
      },
      "Virtual Memory Utilization": {
        "count": 1114,
        "min": 0,
        "max": 0.003204,
        "mean": 0.002437,
        "stdev": 0.000418,
        "median": 0.002257,
        "madev": 0.000375,
        "overflow": 0
      },
      "Latency": {
        "count": 264,
        "min": 0.022156,
        "max": 59.137958,
        "mean": 4.688421,
        "stdev": 10.457898,
        "median": 0.054562,
        "madev": 0.010319,
        "overflow": 0
      },
      "Jitter": {
        "count": 235,
        "min": 0.000001,
        "max": 55.006007,
        "mean": 0.688988,
        "stdev": 3.922597,
        "median": 0.003261,
        "madev": 0.002898,
        "overflow": 0
      },
      "Round Trip Latency": {
        "count": 104,
        "min": 0.037222,
        "max": 29.597834,
        "mean": 5.937912,
        "stdev": 8.332594,
        "median": 1.594705,
        "madev": 1.547968,
        "overflow": 0
      },
      "Round Trip Jitter": {
        "count": 91,
        "min": 0.000113,
        "max": 27.501121,
        "mean": 0.887521,
        "stdev": 3.151164,
        "median": 0.012318,
        "madev": 0.011887,
        "overflow": 0
      }
    }
  },
  "fan_tcp": {
    "256_4": {
      "Errors": 0,
      "Max Discovery Time Delta": 3.217628,
      "Discovery Time Delta": {
        "count": 6,
        "min": 0.113704,
        "max": 3.217628,
        "mean": 1.147428,
        "stdev": 1.459044,
        "median": 0.117473,
        "madev": 0.003487,
        "overflow": 0
      },
      "Cpu Utilization": {
        "count": 326,
        "min": 0,
        "max": 2.261307,
        "mean": 0.046893,
        "stdev": 0.242742,
        "median": 0,
        "madev": 0,
        "overflow": 0
      },
      "Memory Utilization": {
        "count": 326,
        "min": 0,
        "max": 3.102545,
        "mean": 1.90897,
        "stdev": 0.272619,
        "median": 1.704763,
        "madev": 0.104169,
        "overflow": 0
      },
      "Virtual Memory Utilization": {
        "count": 326,
        "min": 0,
        "max": 0.002591,
        "mean": 0.002078,
        "stdev": 0.000266,
        "median": 0.002097,
        "madev": 0,
        "overflow": 0
      },
      "Latency": {
        "count": 80,
        "min": 0.000283,
        "max": 0.001437,
        "mean": 0.000691,
        "stdev": 0.000186,
        "median": 0.000633,
        "madev": 0.000077,
        "overflow": 0
      },
      "Jitter": {
        "count": 72,
        "min": 0,
        "max": 0.00085,
        "mean": 0.00012,
        "stdev": 0.00016,
        "median": 0.000075,
        "madev": 0.000058,
        "overflow": 0
      },
      "Round Trip Latency": {
        "count": 40,
        "min": 0.000739,
        "max": 0.001452,
        "mean": 0.000889,
        "stdev": 0.000163,
        "median": 0.000851,
        "madev": 0.000057,
        "overflow": 0
      },
      "Round Trip Jitter": {
        "count": 36,
        "min": 0.00001,
        "max": 0.000592,
        "mean": 0.00011,
        "stdev": 0.000152,
        "median": 0.000047,
        "madev": 0.000036,
        "overflow": 0
      }
    },
    "256_16": {
      "Errors": 0,
      "Max Discovery Time Delta": 3.209051,
      "Discovery Time Delta": {
        "count": 30,
        "min": 0.109803,
        "max": 3.209051,
        "mean": 2.566478,
        "stdev": 1.224407,
        "median": 3.168105,
        "madev": 0.015319,
        "overflow": 0
      },
      "Cpu Utilization": {
        "count": 1116,
        "min": 0,
        "max": 3.526448,
        "mean": 0.069824,
        "stdev": 0.35653,
        "median": 0,
        "madev": 0,
        "overflow": 0
      },
      "Memory Utilization": {
        "count": 1116,
        "min": 0,
        "max": 10.395886,
        "mean": 2.085181,
        "stdev": 0.513355,
        "median": 1.709652,
        "madev": 0.097579,
        "overflow": 0
      },
      "Virtual Memory Utilization": {
        "count": 1116,
        "min": 0,
        "max": 0.002847,
        "mean": 0.002087,
        "stdev": 0.000268,
        "median": 0.002097,
        "madev": 0,
        "overflow": 0
      },
      "Latency": {
        "count": 320,
        "min": 0.000472,
        "max": 0.003384,
        "mean": 0.001187,
        "stdev": 0.000415,
        "median": 0.001014,
        "madev": 0.000284,
        "overflow": 0
      },
      "Jitter": {
        "count": 288,
        "min": 0,
        "max": 0.001761,
        "mean": 0.000204,
        "stdev": 0.000265,
        "median": 0.000076,
        "madev": 0.000064,
        "overflow": 0
      },
      "Round Trip Latency": {
        "count": 160,
        "min": 0.000758,
        "max": 0.002618,
        "mean": 0.001378,
        "stdev": 0.000359,
        "median": 0.001374,
        "madev": 0.000247,
        "overflow": 0
      },
      "Round Trip Jitter": {
        "count": 144,
        "min": 0,
        "max": 0.00114,
        "mean": 0.000201,
        "stdev": 0.000241,
        "median": 0.000102,
        "madev": 0.000068,
        "overflow": 0
      }
    },
    "4096_4": {
      "Errors": 0,
      "Max Discovery Time Delta": 3.209098,
      "Discovery Time Delta": {
        "count": 6,
        "min": 0.114946,
        "max": 3.209098,
        "mean": 1.14774,
        "stdev": 1.45759,
        "median": 0.118281,
        "madev": 0.002426,
        "overflow": 0
      },
      "Cpu Utilization": {
        "count": 326,
        "min": 0,
        "max": 2.25,
        "mean": 0.048376,
        "stdev": 0.249061,
        "median": 0,
        "madev": 0,
        "overflow": 0
      },
      "Memory Utilization": {
        "count": 326,
        "min": 0,
        "max": 3.10212,
        "mean": 1.937387,
        "stdev": 0.274541,
        "median": 1.706889,
        "madev": 0.004677,
        "overflow": 0
      },
      "Virtual Memory Utilization": {
        "count": 326,
        "min": 0,
        "max": 0.0024,
        "mean": 0.002077,
        "stdev": 0.000266,
        "median": 0.002097,
        "madev": 0,
        "overflow": 0
      },
      "Latency": {
        "count": 80,
        "min": 0.000452,
        "max": 0.001881,
        "mean": 0.00082,
        "stdev": 0.000244,
        "median": 0.000824,
        "madev": 0.000147,
        "overflow": 0
      },
      "Jitter": {
        "count": 72,
        "min": 0,
        "max": 0.001287,
        "mean": 0.000152,
        "stdev": 0.000217,
        "median": 0.000076,
        "madev": 0.00006,
        "overflow": 0
      },
      "Round Trip Latency": {
        "count": 40,
        "min": 0.000743,
        "max": 0.001754,
        "mean": 0.001013,
        "stdev": 0.000225,
        "median": 0.000957,
        "madev": 0.000083,
        "overflow": 0
      },
      "Round Trip Jitter": {
        "count": 36,
        "min": 0.000002,
        "max": 0.000833,
        "mean": 0.000129,
        "stdev": 0.000203,
        "median": 0.00006,
        "madev": 0.000047,
        "overflow": 0
      }
    },
    "4096_16": {
      "Errors": 0,
      "Max Discovery Time Delta": 3.250292,
      "Discovery Time Delta": {
        "count": 30,
        "min": 0.110798,
        "max": 3.250292,
        "mean": 2.396079,
        "stdev": 1.369906,
        "median": 3.211579,
        "madev": 0.019911,
        "overflow": 0
      },
      "Cpu Utilization": {
        "count": 1114,
        "min": 0,
        "max": 3.266332,
        "mean": 0.07129,
        "stdev": 0.34628,
        "median": 0,
        "madev": 0,
        "overflow": 0
      },
      "Memory Utilization": {
        "count": 1114,
        "min": 0,
        "max": 10.489213,
        "mean": 2.090405,
        "stdev": 0.503705,
        "median": 1.706038,
        "madev": 0.092902,
        "overflow": 0
      },
      "Virtual Memory Utilization": {
        "count": 1114,
        "min": 0,
        "max": 0.002847,
        "mean": 0.002087,
        "stdev": 0.000268,
        "median": 0.002097,
        "madev": 0,
        "overflow": 0
      },
      "Latency": {
        "count": 320,
        "min": 0.000585,
        "max": 0.003614,
        "mean": 0.001339,
        "stdev": 0.000492,
        "median": 0.001155,
        "madev": 0.000275,
        "overflow": 0
      },
      "Jitter": {
        "count": 288,
        "min": 0,
        "max": 0.002632,
        "mean": 0.000327,
        "stdev": 0.000357,
        "median": 0.000155,
        "madev": 0.000135,
        "overflow": 0
      },
      "Round Trip Latency": {
        "count": 160,
        "min": 0.000767,
        "max": 0.002746,
        "mean": 0.00153,
        "stdev": 0.000413,
        "median": 0.001487,
        "madev": 0.000294,
        "overflow": 0
      },
      "Round Trip Jitter": {
        "count": 144,
        "min": 0.000001,
        "max": 0.001596,
        "mean": 0.000318,
        "stdev": 0.0003,
        "median": 0.000204,
        "madev": 0.000158,
        "overflow": 0
      }
    },
    "65536_4": {
      "Errors": 0,
      "Max Discovery Time Delta": 3.219822,
      "Discovery Time Delta": {
        "count": 6,
        "min": 0.106302,
        "max": 3.219822,
        "mean": 2.17698,
        "stdev": 1.461522,
        "median": 3.202609,
        "madev": 0.015644,
        "overflow": 0
      },
      "Cpu Utilization": {
        "count": 328,
        "min": 0,
        "max": 2.01005,
        "mean": 0.047386,
        "stdev": 0.239782,
        "median": 0,
        "madev": 0,
        "overflow": 0
      },
      "Memory Utilization": {
        "count": 328,
        "min": 0,
        "max": 3.21458,
        "mean": 1.953741,
        "stdev": 0.309509,
        "median": 1.758123,
        "madev": 0.030188,
        "overflow": 0
      },
      "Virtual Memory Utilization": {
        "count": 328,
        "min": 0,
        "max": 0.0024,
        "mean": 0.002077,
        "stdev": 0.000265,
        "median": 0.002097,
        "madev": 0,
        "overflow": 0
      },
      "Latency": {
        "count": 80,
        "min": 0.001039,
        "max": 0.003584,
        "mean": 0.001741,
        "stdev": 0.000437,
        "median": 0.001683,
        "madev": 0.000324,
        "overflow": 0
      },
      "Jitter": {
        "count": 72,
        "min": 0.000009,
        "max": 0.002091,
        "mean": 0.000391,
        "stdev": 0.000333,
        "median": 0.000366,
        "madev": 0.000167,
        "overflow": 0
      },
      "Round Trip Latency": {
        "count": 40,
        "min": 0.001321,
        "max": 0.003195,
        "mean": 0.001932,
        "stdev": 0.000398,
        "median": 0.001911,
        "madev": 0.000209,
        "overflow": 0
      },
      "Round Trip Jitter": {
        "count": 36,
        "min": 0.000051,
        "max": 0.001336,
        "mean": 0.000351,
        "stdev": 0.000264,
        "median": 0.000297,
        "madev": 0.000105,
        "overflow": 0
      }
    },
    "65536_16": {
      "Errors": 0,
      "Max Discovery Time Delta": 3.239937,
      "Discovery Time Delta": {
        "count": 30,
        "min": 0.117391,
        "max": 3.239937,
        "mean": 1.781585,
        "stdev": 1.537528,
        "median": 3.205439,
        "madev": 0.033092,
        "overflow": 0
      },
      "Cpu Utilization": {
        "count": 1108,
        "min": 0,
        "max": 3.768844,
        "mean": 0.073478,
        "stdev": 0.361368,
        "median": 0,
        "madev": 0,
        "overflow": 0
      },
      "Memory Utilization": {
        "count": 1108,
        "min": 0,
        "max": 10.501756,
        "mean": 2.167242,
        "stdev": 0.464918,
        "median": 1.758123,
        "madev": 0.017432,
        "overflow": 0
      },
      "Virtual Memory Utilization": {
        "count": 1108,
        "min": 0,
        "max": 0.002848,
        "mean": 0.002088,
        "stdev": 0.000268,
        "median": 0.002097,
        "madev": 0,
        "overflow": 0
      },
      "Latency": {
        "count": 320,
        "min": 0.001405,
        "max": 0.010393,
        "mean": 0.003574,
        "stdev": 0.001235,
        "median": 0.002972,
        "madev": 0.000953,
        "overflow": 0
      },
      "Jitter": {
        "count": 288,
        "min": 0,
        "max": 0.006668,
        "mean": 0.000749,
        "stdev": 0.000859,
        "median": 0.000378,
        "madev": 0.000293,
        "overflow": 0
      },
      "Round Trip Latency": {
        "count": 160,
        "min": 0.001714,
        "max": 0.007118,
        "mean": 0.003777,
        "stdev": 0.001054,
        "median": 0.00371,
        "madev": 0.00077,
        "overflow": 0
      },
      "Round Trip Jitter": {
        "count": 144,
        "min": 0.000008,
        "max": 0.003834,
        "mean": 0.000678,
        "stdev": 0.000677,
        "median": 0.000451,
        "madev": 0.00032,
        "overflow": 0
      }
    },
    "1048576_4": {
      "Errors": 0,
      "Max Discovery Time Delta": 0.123891,
      "Discovery Time Delta": {
        "count": 6,
        "min": 0.113174,
        "max": 0.123891,
        "mean": 0.118181,
        "stdev": 0.004035,
        "median": 0.117345,
        "madev": 0.00346,
        "overflow": 0
      },
      "Cpu Utilization": {
        "count": 324,
        "min": 0,
        "max": 2.506266,
        "mean": 0.087362,
        "stdev": 0.294002,
        "median": 0,
        "madev": 0,
        "overflow": 0
      },
      "Memory Utilization": {
        "count": 324,
        "min": 0,
        "max": 3.638486,
        "mean": 2.418245,
        "stdev": 0.358926,
        "median": 2.277269,
        "madev": 0.109909,
        "overflow": 0
      },
      "Virtual Memory Utilization": {
        "count": 324,
        "min": 0,
        "max": 0.002406,
        "mean": 0.002079,
        "stdev": 0.000266,
        "median": 0.002097,
        "madev": 0,
        "overflow": 0
      },
      "Latency": {
        "count": 80,
        "min": 0.006623,
        "max": 0.030791,
        "mean": 0.011878,
        "stdev": 0.003769,
        "median": 0.010962,
        "madev": 0.001768,
        "overflow": 0
      },
      "Jitter": {
        "count": 72,
        "min": 0.000049,
        "max": 0.015766,
        "mean": 0.001983,
        "stdev": 0.002992,
        "median": 0.001,
        "madev": 0.000736,
        "overflow": 0
      },
      "Round Trip Latency": {
        "count": 40,
        "min": 0.007441,
        "max": 0.026275,
        "mean": 0.012274,
        "stdev": 0.003716,
        "median": 0.011419,
        "madev": 0.001726,
        "overflow": 0
      },
      "Round Trip Jitter": {
        "count": 36,
        "min": 0.000016,
        "max": 0.010471,
        "mean": 0.001679,
        "stdev": 0.002567,
        "median": 0.000882,
        "madev": 0.000599,
        "overflow": 0
      }
    },
    "1048576_16": {
      "Errors": 0,
      "Max Discovery Time Delta": 3.258764,
      "Discovery Time Delta": {
        "count": 30,
        "min": 0.114251,
        "max": 3.258764,
        "mean": 2.608002,
        "stdev": 1.242546,
        "median": 3.224025,
        "madev": 0.013055,
        "overflow": 0
      },
      "Cpu Utilization": {
        "count": 1118,
        "min": 0,
        "max": 3.282828,
        "mean": 0.120165,
        "stdev": 0.38914,
        "median": 0,
        "madev": 0,
        "overflow": 0
      },
      "Memory Utilization": {
        "count": 1118,
        "min": 0,
        "max": 10.958825,
        "mean": 2.604335,
        "stdev": 0.609879,
        "median": 2.190745,
        "madev": 0.094815,
        "overflow": 0
      },
      "Virtual Memory Utilization": {
        "count": 1118,
        "min": 0,
        "max": 0.002853,
        "mean": 0.002085,
        "stdev": 0.000268,
        "median": 0.002097,
        "madev": 0,
        "overflow": 0
      },
      "Latency": {
        "count": 320,
        "min": 0.015152,
        "max": 0.067454,
        "mean": 0.027535,
        "stdev": 0.006539,
        "median": 0.025151,
        "madev": 0.00455,
        "overflow": 0
      },
      "Jitter": {
        "count": 288,
        "min": 0.000028,
        "max": 0.024597,
        "mean": 0.003118,
        "stdev": 0.003897,
        "median": 0.001977,
        "madev": 0.001255,
        "overflow": 0
      },
      "Round Trip Latency": {
        "count": 160,
        "min": 0.015776,
        "max": 0.049708,
        "mean": 0.027923,
        "stdev": 0.005689,
        "median": 0.02776,
        "madev": 0.00324,
        "overflow": 0
      },
      "Round Trip Jitter": {
        "count": 144,
        "min": 0.000014,
        "max": 0.014398,
        "mean": 0.002337,
        "stdev": 0.003252,
        "median": 0.001201,
        "madev": 0.000734,
        "overflow": 0
      }
    }
  },
  "showtime_mixed": {
    "10": {
      "Errors": 0,
      "Max Discovery Time Delta": 4.42717,
      "Discovery Time Delta": {
        "count": 1526,
        "min": 0.098998,
        "max": 4.42717,
        "mean": 2.613463,
        "stdev": 1.134023,
        "median": 3.208524,
        "madev": 0.014471,
        "overflow": 0
      },
      "Cpu Utilization": {
        "count": 1067,
        "min": 0,
        "max": 7.286432,
        "mean": 1.01962,
        "stdev": 0.789545,
        "median": 1.005025,
        "madev": 0.253145,
        "overflow": 0
      },
      "Memory Utilization": {
        "count": 1067,
        "min": 0,
        "max": 3.604684,
        "mean": 3.281526,
        "stdev": 0.341958,
        "median": 3.463099,
        "madev": 0.094603,
        "overflow": 0
      },
      "Virtual Memory Utilization": {
        "count": 1067,
        "min": 0,
        "max": 0.005972,
        "mean": 0.005191,
        "stdev": 0.000541,
        "median": 0.005448,
        "madev": 0,
        "overflow": 0
      },
      "Latency": {
        "count": 40423,
        "min": 0.000149,
        "max": 1.230585,
        "mean": 0.000814,
        "stdev": 0.006435,
        "median": 0.000777,
        "madev": 0.000141,
        "overflow": 0
      },
      "Jitter": {
        "count": 39660,
        "min": 0,
        "max": 1.229543,
        "mean": 0.000127,
        "stdev": 0.006492,
        "median": 0.00005,
        "madev": 0.000035,
        "overflow": 0
      },
      "Round Trip Latency": {
        "count": 0,
        "min": 0,
        "max": 0,
        "mean": 0,
        "stdev": 0,
        "median": 0,
        "madev": 0,
        "overflow": 0
      },
      "Round Trip Jitter": {
        "count": 0,
        "min": 0,
        "max": 0,
        "mean": 0,
        "stdev": 0,
        "median": 0,
        "madev": 0,
        "overflow": 0
      }
    },
    "20": {
      "Errors": 0,
      "Max Discovery Time Delta": 4.323762,
      "Discovery Time Delta": {
        "count": 5846,
        "min": 0.097474,
        "max": 4.323762,
        "mean": 2.898633,
        "stdev": 1.05752,
        "median": 3.291959,
        "madev": 0.063375,
        "overflow": 0
      },
      "Cpu Utilization": {
        "count": 2037,
        "min": 0,
        "max": 17.873454,
        "mean": 1.728773,
        "stdev": 1.403459,
        "median": 1.511335,
        "madev": 0.498715,
        "overflow": 0
      },
      "Memory Utilization": {
        "count": 2037,
        "min": 0,
        "max": 3.888917,
        "mean": 3.416672,
        "stdev": 0.356721,
        "median": 3.486271,
        "madev": 0.085461,
        "overflow": 0
      },
      "Virtual Memory Utilization": {
        "count": 2037,
        "min": 0,
        "max": 0.005972,
        "mean": 0.005331,
        "stdev": 0.000555,
        "median": 0.005448,
        "madev": 0.000191,
        "overflow": 0
      },
      "Latency": {
        "count": 155469,
        "min": 0.000206,
        "max": 2.221194,
        "mean": 0.00152,
        "stdev": 0.033705,
        "median": 0.000808,
        "madev": 0.000117,
        "overflow": 12040
      },
      "Jitter": {
        "count": 152546,
        "min": 0,
        "max": 2.219871,
        "mean": 0.00083,
        "stdev": 0.034019,
        "median": 0.000074,
        "madev": 0.000049,
        "overflow": 10440
      },
      "Round Trip Latency": {
        "count": 0,
        "min": 0,
        "max": 0,
        "mean": 0,
        "stdev": 0,
        "median": 0,
        "madev": 0,
        "overflow": 0
      },
      "Round Trip Jitter": {
        "count": 0,
        "min": 0,
        "max": 0,
        "mean": 0,
        "stdev": 0,
        "median": 0,
        "madev": 0,
        "overflow": 0
      }
    },
    "30": {
      "Errors": 0,
      "Max Discovery Time Delta": 4.551081,
      "Discovery Time Delta": {
        "count": 12966,
        "min": 0.093081,
        "max": 4.551081,
        "mean": 3.026546,
        "stdev": 0.98678,
        "median": 3.349683,
        "madev": 0.088888,
        "overflow": 0
      },
      "Cpu Utilization": {
        "count": 2911,
        "min": 0,
        "max": 25.575448,
        "mean": 2.782163,
        "stdev": 2.310932,
        "median": 2.518892,
        "madev": 0.513879,
        "overflow": 0
      },
      "Memory Utilization": {
        "count": 2911,
        "min": 0,
        "max": 5.815837,
        "mean": 3.678645,
        "stdev": 0.38845,
        "median": 3.651879,
        "madev": 0.094603,
        "overflow": 0
      },
      "Virtual Memory Utilization": {
        "count": 2911,
        "min": 0,
        "max": 0.00874,
        "mean": 0.005468,
        "stdev": 0.000576,
        "median": 0.005448,
        "madev": 0,
        "overflow": 0
      },
      "Latency": {
        "count": 345330,
        "min": 0.00015,
        "max": 2.22111,
        "mean": 0.001332,
        "stdev": 0.024231,
        "median": 0.000862,
        "madev": 0.000116,
        "overflow": 96203
      },
      "Jitter": {
        "count": 338847,
        "min": 0,
        "max": 2.220177,
        "mean": 0.000591,
        "stdev": 0.024454,
        "median": 0.000096,
        "madev": 0.000064,
        "overflow": 91642
      },
      "Round Trip Latency": {
        "count": 0,
        "min": 0,
        "max": 0,
        "mean": 0,
        "stdev": 0,
        "median": 0,
        "madev": 0,
        "overflow": 0
      },
      "Round Trip Jitter": {
        "count": 0,
        "min": 0,
        "max": 0,
        "mean": 0,
        "stdev": 0,
        "median": 0,
        "madev": 0,
        "overflow": 0
      }
    },
    "40": {
      "Errors": 0,
      "Max Discovery Time Delta": 4.719074,
      "Discovery Time Delta": {
        "count": 22886,
        "min": 0.089067,
        "max": 4.719074,
        "mean": 3.246555,
        "stdev": 0.747184,
        "median": 3.423729,
        "madev": 0.095723,
        "overflow": 0
      },
      "Cpu Utilization": {
        "count": 2910,
        "min": 0,
        "max": 63.185379,
        "mean": 4.724675,
        "stdev": 4.181345,
        "median": 4.069632,
        "madev": 1.277754,
        "overflow": 0
      },
      "Memory Utilization": {
        "count": 2910,
        "min": 0,
        "max": 9.437103,
        "mean": 4.886672,
        "stdev": 0.538534,
        "median": 3.750946,
        "madev": 0.19367,
        "overflow": 0
      },
      "Virtual Memory Utilization": {
        "count": 2910,
        "min": 0,
        "max": 0.013949,
        "mean": 0.00722,
        "stdev": 0.000794,
        "median": 0.005448,
        "madev": 0.000191,
        "overflow": 0
      },
      "Latency": {
        "count": 610062,
        "min": 0.000184,
        "max": 2.221087,
        "mean": 0.001077,
        "stdev": 0.005668,
        "median": 0.000918,
        "madev": 0.00014,
        "overflow": 250513
      },
      "Jitter": {
        "count": 598619,
        "min": 0,
        "max": 2.219682,
        "mean": 0.000302,
        "stdev": 0.005719,
        "median": 0.000111,
        "madev": 0.000074,
        "overflow": 242432
      },
      "Round Trip Latency": {
        "count": 0,
        "min": 0,
        "max": 0,
        "mean": 0,
        "stdev": 0,
        "median": 0,
        "madev": 0,
        "overflow": 0
      },
      "Round Trip Jitter": {
        "count": 0,
        "min": 0,
        "max": 0,
        "mean": 0,
        "stdev": 0,
        "median": 0,
        "madev": 0,
        "overflow": 0
      }
    },
    "50": {
      "Errors": 0,
      "Max Discovery Time Delta": 5.605614,
      "Discovery Time Delta": {
        "count": 35606,
        "min": 0.06097,
        "max": 5.605614,
        "mean": 3.262425,
        "stdev": 0.870456,
        "median": 3.496493,
        "madev": 0.134341,
        "overflow": 0
      },
      "Cpu Utilization": {
        "count": 2914,
        "min": 0,
        "max": 77.142857,
        "mean": 6.667318,
        "stdev": 5.999005,
        "median": 5.85048,
        "madev": 1.78892,
        "overflow": 0
      },
      "Memory Utilization": {
        "count": 2914,
        "min": 0,
        "max": 9.573799,
        "mean": 6.171692,
        "stdev": 0.728632,
        "median": 7.212344,
        "madev": 0.342483,
        "overflow": 0
      },
      "Virtual Memory Utilization": {
        "count": 2914,
        "min": 0,
        "max": 0.01433,
        "mean": 0.008976,
        "stdev": 0.001057,
        "median": 0.010705,
        "madev": 0.000191,
        "overflow": 0
      },
      "Latency": {
        "count": 949360,
        "min": 0.000179,
        "max": 2.22565,
        "mean": 0.0019,
        "stdev": 0.026485,
        "median": 0.00098,
        "madev": 0.000171,
        "overflow": 470133
      },
      "Jitter": {
        "count": 931557,
        "min": 0,
        "max": 2.22192,
        "mean": 0.001215,
        "stdev": 0.026697,
        "median": 0.000167,
        "madev": 0.000121,
        "overflow": 454931
      },
      "Round Trip Latency": {
        "count": 0,
        "min": 0,
        "max": 0,
        "mean": 0,
        "stdev": 0,
        "median": 0,
        "madev": 0,
        "overflow": 0
      },
      "Round Trip Jitter": {
        "count": 0,
        "min": 0,
        "max": 0,
        "mean": 0,
        "stdev": 0,
        "median": 0,
        "madev": 0,
        "overflow": 0
      }
    },
    "70": {
      "Errors": 0,
      "Max Discovery Time Delta": 6.085421,
      "Discovery Time Delta": {
        "count": 69446,
        "min": 0.06322,
        "max": 6.085421,
        "mean": 3.645341,
        "stdev": 0.762359,
        "median": 3.762483,
        "madev": 0.192019,
        "overflow": 0
      },
      "Cpu Utilization": {
        "count": 2932,
        "min": 0,
        "max": 98.499291,
        "mean": 12.760434,
        "stdev": 8.672569,
        "median": 11.658031,
        "madev": 2.69821,
        "overflow": 0
      },
      "Memory Utilization": {
        "count": 2932,
        "min": 0,
        "max": 13.896613,
        "mean": 8.912869,
        "stdev": 1.141707,
        "median": 7.81929,
        "madev": 0.230873,
        "overflow": 0
      },
      "Virtual Memory Utilization": {
        "count": 2932,
        "min": 0,
        "max": 0.01954,
        "mean": 0.012595,
        "stdev": 0.001584,
        "median": 0.011086,
        "madev": 0.000381,
        "overflow": 0
      },
      "Latency": {
        "count": 1850884,
        "min": 0.000055,
        "max": 3.21114,
        "mean": 0.003816,
        "stdev": 0.061766,
        "median": 0.001111,
        "madev": 0.000188,
        "overflow": 1145237
      },
      "Jitter": {
        "count": 1816161,
        "min": 0,
        "max": 3.209961,
        "mean": 0.003057,
        "stdev": 0.061956,
        "median": 0.000197,
        "madev": 0.000141,
        "overflow": 1111295
      },
      "Round Trip Latency": {
        "count": 0,
        "min": 0,
        "max": 0,
        "mean": 0,
        "stdev": 0,
        "median": 0,
        "madev": 0,
        "overflow": 0
      },
      "Round Trip Jitter": {
        "count": 0,
        "min": 0,
        "max": 0,
        "mean": 0,
        "stdev": 0,
        "median": 0,
        "madev": 0,
        "overflow": 0
      }
    },
    "80": {
      "Errors": 0,
      "Max Discovery Time Delta": 5.680247,
      "Discovery Time Delta": {
        "count": 90392,
        "min": 0.054472,
        "max": 5.680247,
        "mean": 3.775348,
        "stdev": 0.632197,
        "median": 3.867971,
        "madev": 0.183806,
        "overflow": 0
      },
      "Cpu Utilization": {
        "count": 2915,
        "min": 0,
        "max": 97.089947,
        "mean": 16.332826,
        "stdev": 9.461804,
        "median": 15.104167,
        "madev": 3.713236,
        "overflow": 0
      },
      "Memory Utilization": {
        "count": 2915,
        "min": 0,
        "max": 14.510787,
        "mean": 10.546079,
        "stdev": 1.208726,
        "median": 11.741158,
        "madev": 0.408174,
        "overflow": 0
      },
      "Virtual Memory Utilization": {
        "count": 2915,
        "min": 0,
        "max": 0.019731,
        "mean": 0.014357,
        "stdev": 0.001601,
        "median": 0.016153,
        "madev": 0.000381,
        "overflow": 0
      },
      "Latency": {
        "count": 2408756,
        "min": 0.000134,
        "max": 3.210618,
        "mean": 0.004787,
        "stdev": 0.073531,
        "median": 0.001168,
        "madev": 0.000205,
        "overflow": 1603159
      },
      "Jitter": {
        "count": 2363560,
        "min": 0,
        "max": 3.20928,
        "mean": 0.003936,
        "stdev": 0.074071,
        "median": 0.000208,
        "madev": 0.000144,
        "overflow": 1557963
      },
      "Round Trip Latency": {
        "count": 0,
        "min": 0,
        "max": 0,
        "mean": 0,
        "stdev": 0,
        "median": 0,
        "madev": 0,
        "overflow": 0
      },
      "Round Trip Jitter": {
        "count": 0,
        "min": 0,
        "max": 0,
        "mean": 0,
        "stdev": 0,
        "median": 0,
        "madev": 0,
        "overflow": 0
      }
    }
  }
}